{
    "intro": "Je suis actuellement en cinquième année d'études d'ingénieur en informatique (promo 2021 à l'[EPITA](https://epita.fr \"Site web d'EPITA\")).",
    "apropos": "Toujours au courant des dernières actualités technologiques, je suis très actif dans les projets de groupe.\n\nJe suis à l'aise dans un vaste pannel de technologies et langages, allant de la programmation pour Arduino, en passant par l'assembleur x86_64, jusqu'à des langages de haut niveau comme le Python.",
    "cv": "https://files.thetoto.fr/private/cv.pdf",
    "skills": [
        {
            "icons": [
                "nf nf-custom-c",
                "nf nf-custom-cpp"
            ],
            "hints": [
                "C",
                "C++"
            ],
            "stars": 4
        },
        {
            "icons": [
                "nf nf-dev-python"
            ],
            "hints": [
                "Python",
                "Django"
            ],
            "stars": 4.5
        },
        {
            "icons": [
                "nf nf-linux-archlinux",
                "nf nf-dev-git"
            ],
            "hints": [
                "Linux (ArchLinux)",
                "Git"
            ],
            "stars": 4.5
        },
        {
            "icons": [
                "nf nf-linux-docker"
            ],
            "hints": [
                "Docker"
            ],
            "stars": 4.5
        },
        {
            "text": "Assembly x86_64",
            "stars": 2.5
        },
        {
            "text": "Learn new things",
            "stars": 5,
            "heart": true
        }
    ]
}